infogroove/__init__.py
infogroove/cli.py
infogroove/core.py
infogroove/exceptions.py
infogroove/formula.py
infogroove/loader.py
infogroove/models.py
infogroove/renderer.py
infogroove/utils.py
infogroove-0.5.2.dist-info/METADATA
infogroove-0.5.2.dist-info/WHEEL
infogroove-0.5.2.dist-info/entry_points.txt
infogroove-0.5.2.dist-info/RECORD
