Metadata-Version: 2.4
Name: infogroove
Version: 0.5.2
Summary: Programmable infographic generation powered by sympy and svg.py
Project-URL: Homepage, https://github.com/comfuture/infogroove
Project-URL: Repository, https://github.com/comfuture/infogroove
Project-URL: Documentation, https://github.com/comfuture/infogroove/tree/main/docs
Project-URL: Issues, https://github.com/comfuture/infogroove/issues
Author-email: comfuture <comfuture@gmail.com>
License: MIT License
Keywords: data-visualization,infographic,svg,sympy,templating
Classifier: Development Status :: 3 - Alpha
Classifier: Intended Audience :: Developers
Classifier: License :: OSI Approved :: MIT License
Classifier: Programming Language :: Python
Classifier: Programming Language :: Python :: 3
Classifier: Programming Language :: Python :: 3.11
Classifier: Programming Language :: Python :: 3.12
Classifier: Topic :: Multimedia :: Graphics :: Graphics Conversion
Classifier: Topic :: Scientific/Engineering :: Visualization
Requires-Python: >=3.11
Requires-Dist: jsonschema>=4.23.0
Requires-Dist: svg-py>=1.9.1
Requires-Dist: sympy>=1.14.0
Provides-Extra: dev
Requires-Dist: pytest>=8; extra == 'dev'
